{
    "package": "tf.veriny.lilligant.mixin",
    "minVersion": "0.8.5",
    "required": true,
    "mixins": [
        "deletespawners.MakeMobSpawnersRemoveThemselves",
        "enchant.AddEnchantmentInterceptorsToHelper",
        "enchant.ImplAerialAffinity",
        "entityblock.DontAllowAddingEntities",
        "mandatorypeaceful.EnforcePeacefulInGame",
        "peai.ImplPEAIMiningSpeed",
        "peai.ImplPEAISuitableFor",
        "portalblock.DestroyExistingPortals",
        "portalblock.InterceptPortalCreation",
        "recipebook.VaporiseServerSideRecipeBook",
        "sniffer.MakeSnifferCooldownConfigurable",
        "sweetberrybush.SweetBerriesDontSlow"
    ],
    "client": [
        "jvmargs.InjectArgumentsWarningScreen",
        "mandatorypeaceful.EnforcePeacefulOnWorldCreationScreen",
        "mandatorypeaceful.LockDifficultyButtonOnWorldCreateScreen",
        "narrator.DontSpamNarratorErrors",
        "recipebook.RemoveClientSideBookWidget"
    ]
}
